kaia/__init__.py
kaia_kaia-0.0.0.dist-info/METADATA
kaia_kaia-0.0.0.dist-info/WHEEL
kaia_kaia-0.0.0.dist-info/top_level.txt
kaia_kaia-0.0.0.dist-info/RECORD
