Metadata-Version: 2.1
Name: kaia-kaia
Version: 0.0.0
Summary: One of the modules for KAIA project
Author-email: Yuri Okulovsky <yuri.okulovsky@gmail.com>
License: GPLv3
Requires-Python: <4.0,>=3.10
